[{"timestamp":1588703530301,"files":[{"filename":"sw-esm.js","previous":747,"size":741,"diff":-6},{"filename":"sw.js","previous":744,"size":738,"diff":-6},{"filename":"polyfills.7a9c4.esm.js","previous":2019,"size":0,"diff":-2019},{"filename":"route-Home.chunk.d8f82.css","previous":20659,"size":20659,"diff":0},{"filename":"polyfills.1c45d.js","previous":2019,"size":0,"diff":-2019},{"filename":"bundle.fdc37.esm.js","previous":7229,"size":0,"diff":-7229},{"filename":"route-Home.chunk.ea552.esm.js","previous":118921,"size":118921,"diff":0},{"filename":"bundle.f2e06.js","previous":7290,"size":0,"diff":-7290},{"filename":"route-Home.chunk.dc651.js","previous":119745,"size":119745,"diff":0},{"filename":"bundle.3343e.esm.js","previous":0,"size":7214,"diff":7214},{"filename":"polyfills.851f4.esm.js","previous":0,"size":2012,"diff":2012},{"filename":"bundle.d1041.js","previous":0,"size":7285,"diff":7285},{"filename":"polyfills.1a596.js","previous":0,"size":2013,"diff":2013}]},{"timestamp":1588703378559,"files":[{"filename":"sw-esm.js","previous":747,"size":747,"diff":0},{"filename":"sw.js","previous":744,"size":744,"diff":0},{"filename":"polyfills.7a9c4.esm.js","previous":2019,"size":2019,"diff":0},{"filename":"route-Home.chunk.d8f82.css","previous":20659,"size":20659,"diff":0},{"filename":"polyfills.1c45d.js","previous":2019,"size":2019,"diff":0},{"filename":"bundle.5d78a.esm.js","previous":23658,"size":0,"diff":-23658},{"filename":"route-Home.chunk.4d0ca.esm.js","previous":103203,"size":0,"diff":-103203},{"filename":"bundle.f2ad6.js","previous":23709,"size":0,"diff":-23709},{"filename":"route-Home.chunk.d9597.js","previous":104088,"size":0,"diff":-104088},{"filename":"bundle.fdc37.esm.js","previous":0,"size":7229,"diff":7229},{"filename":"route-Home.chunk.ea552.esm.js","previous":0,"size":118921,"diff":118921},{"filename":"bundle.f2e06.js","previous":0,"size":7290,"diff":7290},{"filename":"route-Home.chunk.dc651.js","previous":0,"size":119745,"diff":119745}]},{"timestamp":1588694220650,"files":[{"filename":"sw-esm.js","previous":747,"size":747,"diff":0},{"filename":"sw.js","previous":744,"size":744,"diff":0},{"filename":"polyfills.7a9c4.esm.js","previous":2019,"size":2019,"diff":0},{"filename":"route-Home.chunk.d8f82.css","previous":20659,"size":20659,"diff":0},{"filename":"polyfills.1c45d.js","previous":2019,"size":2019,"diff":0},{"filename":"bundle.fdc37.esm.js","previous":7229,"size":0,"diff":-7229},{"filename":"route-Home.chunk.ea552.esm.js","previous":118921,"size":0,"diff":-118921},{"filename":"bundle.f2e06.js","previous":7290,"size":0,"diff":-7290},{"filename":"route-Home.chunk.dc651.js","previous":119745,"size":0,"diff":-119745},{"filename":"bundle.5d78a.esm.js","previous":0,"size":23658,"diff":23658},{"filename":"route-Home.chunk.4d0ca.esm.js","previous":0,"size":103203,"diff":103203},{"filename":"bundle.f2ad6.js","previous":0,"size":23709,"diff":23709},{"filename":"route-Home.chunk.d9597.js","previous":0,"size":104088,"diff":104088}]},{"timestamp":1588589904784,"files":[{"filename":"sw-esm.js","previous":747,"size":747,"diff":0},{"filename":"sw.js","previous":744,"size":744,"diff":0},{"filename":"polyfills.7a9c4.esm.js","previous":2019,"size":2019,"diff":0},{"filename":"route-Home.chunk.d8f82.css","previous":20659,"size":20659,"diff":0},{"filename":"polyfills.1c45d.js","previous":2019,"size":2019,"diff":0},{"filename":"bundle.f54af.esm.js","previous":7228,"size":0,"diff":-7228},{"filename":"route-Home.chunk.ed8e2.esm.js","previous":110374,"size":0,"diff":-110374},{"filename":"bundle.b9f67.js","previous":7293,"size":0,"diff":-7293},{"filename":"route-Home.chunk.52859.js","previous":111191,"size":0,"diff":-111191},{"filename":"bundle.fdc37.esm.js","previous":0,"size":7229,"diff":7229},{"filename":"route-Home.chunk.ea552.esm.js","previous":0,"size":118921,"diff":118921},{"filename":"bundle.f2e06.js","previous":0,"size":7290,"diff":7290},{"filename":"route-Home.chunk.dc651.js","previous":0,"size":119745,"diff":119745}]},{"timestamp":1588508711427,"files":[{"filename":"sw-esm.js","previous":747,"size":747,"diff":0},{"filename":"sw.js","previous":744,"size":744,"diff":0},{"filename":"polyfills.7a9c4.esm.js","previous":2019,"size":2019,"diff":0},{"filename":"route-Home.chunk.d8f82.css","previous":20659,"size":20659,"diff":0},{"filename":"polyfills.1c45d.js","previous":2019,"size":2019,"diff":0},{"filename":"bundle.4fd21.esm.js","previous":7231,"size":0,"diff":-7231},{"filename":"route-Home.chunk.7f5a8.esm.js","previous":110390,"size":0,"diff":-110390},{"filename":"bundle.4098e.js","previous":7289,"size":0,"diff":-7289},{"filename":"route-Home.chunk.d0e90.js","previous":111205,"size":0,"diff":-111205},{"filename":"bundle.f54af.esm.js","previous":0,"size":7228,"diff":7228},{"filename":"route-Home.chunk.ed8e2.esm.js","previous":0,"size":110374,"diff":110374},{"filename":"bundle.b9f67.js","previous":0,"size":7293,"diff":7293},{"filename":"route-Home.chunk.52859.js","previous":0,"size":111191,"diff":111191}]},{"timestamp":1588504408100,"files":[{"filename":"sw-esm.js","previous":747,"size":747,"diff":0},{"filename":"sw.js","previous":744,"size":744,"diff":0},{"filename":"polyfills.7a9c4.esm.js","previous":2019,"size":2019,"diff":0},{"filename":"route-Home.chunk.d8f82.css","previous":20659,"size":20659,"diff":0},{"filename":"polyfills.1c45d.js","previous":2019,"size":2019,"diff":0},{"filename":"bundle.a4ce0.esm.js","previous":7230,"size":0,"diff":-7230},{"filename":"route-Home.chunk.74c6c.esm.js","previous":110245,"size":0,"diff":-110245},{"filename":"bundle.6d888.js","previous":7292,"size":0,"diff":-7292},{"filename":"route-Home.chunk.e9698.js","previous":111046,"size":0,"diff":-111046},{"filename":"bundle.4fd21.esm.js","previous":0,"size":7231,"diff":7231},{"filename":"route-Home.chunk.7f5a8.esm.js","previous":0,"size":110390,"diff":110390},{"filename":"bundle.4098e.js","previous":0,"size":7289,"diff":7289},{"filename":"route-Home.chunk.d0e90.js","previous":0,"size":111205,"diff":111205}]},{"timestamp":1588490634423,"files":[{"filename":"sw-esm.js","previous":747,"size":747,"diff":0},{"filename":"sw.js","previous":744,"size":744,"diff":0},{"filename":"polyfills.7a9c4.esm.js","previous":2019,"size":2019,"diff":0},{"filename":"route-Home.chunk.d8f82.css","previous":20659,"size":20659,"diff":0},{"filename":"polyfills.1c45d.js","previous":2019,"size":2019,"diff":0},{"filename":"bundle.c6684.esm.js","previous":7231,"size":0,"diff":-7231},{"filename":"route-Home.chunk.259fe.esm.js","previous":107723,"size":0,"diff":-107723},{"filename":"bundle.5cd26.js","previous":7210,"size":0,"diff":-7210},{"filename":"route-Home.chunk.ef66d.js","previous":108488,"size":0,"diff":-108488},{"filename":"bundle.a4ce0.esm.js","previous":0,"size":7230,"diff":7230},{"filename":"route-Home.chunk.74c6c.esm.js","previous":0,"size":110245,"diff":110245},{"filename":"bundle.6d888.js","previous":0,"size":7292,"diff":7292},{"filename":"route-Home.chunk.e9698.js","previous":0,"size":111046,"diff":111046}]},{"timestamp":1588405557490,"files":[{"filename":"sw-esm.js","previous":747,"size":747,"diff":0},{"filename":"sw.js","previous":744,"size":744,"diff":0},{"filename":"polyfills.7a9c4.esm.js","previous":2019,"size":2019,"diff":0},{"filename":"route-Home.chunk.d8f82.css","previous":20659,"size":20659,"diff":0},{"filename":"polyfills.1c45d.js","previous":2019,"size":2019,"diff":0},{"filename":"bundle.edbe4.esm.js","previous":7230,"size":0,"diff":-7230},{"filename":"route-Home.chunk.68f15.esm.js","previous":107732,"size":0,"diff":-107732},{"filename":"bundle.8cea8.js","previous":7210,"size":0,"diff":-7210},{"filename":"route-Home.chunk.21896.js","previous":108499,"size":0,"diff":-108499},{"filename":"bundle.c6684.esm.js","previous":0,"size":7231,"diff":7231},{"filename":"route-Home.chunk.259fe.esm.js","previous":0,"size":107723,"diff":107723},{"filename":"bundle.5cd26.js","previous":0,"size":7210,"diff":7210},{"filename":"route-Home.chunk.ef66d.js","previous":0,"size":108488,"diff":108488}]},{"timestamp":1588005644302,"files":[{"filename":"sw-esm.js","previous":747,"size":747,"diff":0},{"filename":"sw.js","previous":744,"size":744,"diff":0},{"filename":"polyfills.7a9c4.esm.js","previous":2019,"size":2019,"diff":0},{"filename":"route-Home.chunk.d8f82.css","previous":20659,"size":20659,"diff":0},{"filename":"route-Home.chunk.13dca.esm.js","previous":107717,"size":0,"diff":-107717},{"filename":"polyfills.1c45d.js","previous":2019,"size":2019,"diff":0},{"filename":"route-Home.chunk.e4eb8.js","previous":108487,"size":0,"diff":-108487},{"filename":"bundle.d006d.esm.js","previous":7251,"size":0,"diff":-7251},{"filename":"bundle.b07e4.js","previous":7230,"size":0,"diff":-7230},{"filename":"bundle.edbe4.esm.js","previous":0,"size":7230,"diff":7230},{"filename":"route-Home.chunk.68f15.esm.js","previous":0,"size":107732,"diff":107732},{"filename":"bundle.8cea8.js","previous":0,"size":7210,"diff":7210},{"filename":"route-Home.chunk.21896.js","previous":0,"size":108499,"diff":108499}]},{"timestamp":1588005061122,"files":[{"filename":"sw-esm.js","previous":747,"size":747,"diff":0},{"filename":"sw.js","previous":744,"size":744,"diff":0},{"filename":"polyfills.7a9c4.esm.js","previous":2019,"size":2019,"diff":0},{"filename":"route-Home.chunk.d8f82.css","previous":20659,"size":20659,"diff":0},{"filename":"route-Home.chunk.13dca.esm.js","previous":107717,"size":107717,"diff":0},{"filename":"polyfills.1c45d.js","previous":2019,"size":2019,"diff":0},{"filename":"route-Home.chunk.e4eb8.js","previous":108487,"size":108487,"diff":0},{"filename":"bundle.86289.esm.js","previous":7252,"size":0,"diff":-7252},{"filename":"bundle.255ba.js","previous":7230,"size":0,"diff":-7230},{"filename":"bundle.d006d.esm.js","previous":0,"size":7251,"diff":7251},{"filename":"bundle.b07e4.js","previous":0,"size":7230,"diff":7230}]},{"timestamp":1588004790504,"files":[{"filename":"sw-esm.js","previous":747,"size":747,"diff":0},{"filename":"sw.js","previous":744,"size":744,"diff":0},{"filename":"bundle.1bbb5.esm.js","previous":7307,"size":0,"diff":-7307},{"filename":"polyfills.7a9c4.esm.js","previous":2019,"size":2019,"diff":0},{"filename":"route-Home.chunk.d8f82.css","previous":20659,"size":20659,"diff":0},{"filename":"route-Home.chunk.13dca.esm.js","previous":107717,"size":107717,"diff":0},{"filename":"bundle.7a8b3.js","previous":7268,"size":0,"diff":-7268},{"filename":"polyfills.1c45d.js","previous":2019,"size":2019,"diff":0},{"filename":"route-Home.chunk.e4eb8.js","previous":108487,"size":108487,"diff":0},{"filename":"bundle.86289.esm.js","previous":0,"size":7252,"diff":7252},{"filename":"bundle.255ba.js","previous":0,"size":7230,"diff":7230}]},{"timestamp":1588004652598,"files":[{"filename":"ssr-bundle.d8f82.css","previous":6822,"size":0,"diff":-6822},{"filename":"ssr-bundle.js","previous":117740,"size":0,"diff":-117740},{"filename":"sw-esm.js","previous":0,"size":747,"diff":747},{"filename":"sw.js","previous":0,"size":744,"diff":744},{"filename":"bundle.1bbb5.esm.js","previous":0,"size":7307,"diff":7307},{"filename":"polyfills.7a9c4.esm.js","previous":0,"size":2019,"diff":2019},{"filename":"route-Home.chunk.d8f82.css","previous":0,"size":20659,"diff":20659},{"filename":"route-Home.chunk.13dca.esm.js","previous":0,"size":107717,"diff":107717},{"filename":"bundle.7a8b3.js","previous":0,"size":7268,"diff":7268},{"filename":"polyfills.1c45d.js","previous":0,"size":2019,"diff":2019},{"filename":"route-Home.chunk.e4eb8.js","previous":0,"size":108487,"diff":108487}]},{"timestamp":1588004607470,"files":[{"filename":"sw-esm.js","previous":747,"size":0,"diff":-747},{"filename":"sw.js","previous":744,"size":0,"diff":-744},{"filename":"bundle.3675b.esm.js","previous":7295,"size":0,"diff":-7295},{"filename":"polyfills.7a9c4.esm.js","previous":2019,"size":0,"diff":-2019},{"filename":"route-Home.chunk.d8f82.css","previous":20659,"size":0,"diff":-20659},{"filename":"route-Home.chunk.13dca.esm.js","previous":107717,"size":0,"diff":-107717},{"filename":"bundle.f2a9e.js","previous":7254,"size":0,"diff":-7254},{"filename":"polyfills.1c45d.js","previous":2019,"size":0,"diff":-2019},{"filename":"route-Home.chunk.e4eb8.js","previous":108487,"size":0,"diff":-108487},{"filename":"ssr-bundle.d8f82.css","previous":0,"size":6822,"diff":6822},{"filename":"ssr-bundle.js","previous":0,"size":117740,"diff":117740}]},{"timestamp":1587978121017,"files":[{"filename":"ssr-bundle.d8f82.css","previous":6822,"size":0,"diff":-6822},{"filename":"ssr-bundle.js","previous":117721,"size":0,"diff":-117721},{"filename":"sw-esm.js","previous":0,"size":747,"diff":747},{"filename":"sw.js","previous":0,"size":744,"diff":744},{"filename":"bundle.3675b.esm.js","previous":0,"size":7295,"diff":7295},{"filename":"polyfills.7a9c4.esm.js","previous":0,"size":2019,"diff":2019},{"filename":"route-Home.chunk.d8f82.css","previous":0,"size":20659,"diff":20659},{"filename":"route-Home.chunk.13dca.esm.js","previous":0,"size":107717,"diff":107717},{"filename":"bundle.f2a9e.js","previous":0,"size":7254,"diff":7254},{"filename":"polyfills.1c45d.js","previous":0,"size":2019,"diff":2019},{"filename":"route-Home.chunk.e4eb8.js","previous":0,"size":108487,"diff":108487}]},{"timestamp":1587977982744,"files":[{"filename":"sw-esm.js","previous":747,"size":0,"diff":-747},{"filename":"sw.js","previous":744,"size":0,"diff":-744},{"filename":"bundle.39b36.esm.js","previous":7294,"size":0,"diff":-7294},{"filename":"polyfills.7a9c4.esm.js","previous":2019,"size":0,"diff":-2019},{"filename":"route-Home.chunk.d8f82.css","previous":20659,"size":0,"diff":-20659},{"filename":"route-Home.chunk.22ea6.esm.js","previous":107714,"size":0,"diff":-107714},{"filename":"bundle.d3162.js","previous":7256,"size":0,"diff":-7256},{"filename":"polyfills.1c45d.js","previous":2019,"size":0,"diff":-2019},{"filename":"route-Home.chunk.c2827.js","previous":108482,"size":0,"diff":-108482},{"filename":"ssr-bundle.d8f82.css","previous":0,"size":6822,"diff":6822},{"filename":"ssr-bundle.js","previous":0,"size":117721,"diff":117721}]},{"timestamp":1587977094684,"files":[{"filename":"ssr-bundle.d8f82.css","previous":6822,"size":0,"diff":-6822},{"filename":"ssr-bundle.js","previous":117713,"size":0,"diff":-117713},{"filename":"sw-esm.js","previous":0,"size":747,"diff":747},{"filename":"sw.js","previous":0,"size":744,"diff":744},{"filename":"bundle.39b36.esm.js","previous":0,"size":7294,"diff":7294},{"filename":"polyfills.7a9c4.esm.js","previous":0,"size":2019,"diff":2019},{"filename":"route-Home.chunk.d8f82.css","previous":0,"size":20659,"diff":20659},{"filename":"route-Home.chunk.22ea6.esm.js","previous":0,"size":107714,"diff":107714},{"filename":"bundle.d3162.js","previous":0,"size":7256,"diff":7256},{"filename":"polyfills.1c45d.js","previous":0,"size":2019,"diff":2019},{"filename":"route-Home.chunk.c2827.js","previous":0,"size":108482,"diff":108482}]},{"timestamp":1587976993909,"files":[{"filename":"sw-esm.js","previous":747,"size":0,"diff":-747},{"filename":"sw.js","previous":744,"size":0,"diff":-744},{"filename":"bundle.042ca.esm.js","previous":7275,"size":0,"diff":-7275},{"filename":"polyfills.7a9c4.esm.js","previous":2019,"size":0,"diff":-2019},{"filename":"route-Home.chunk.d8f82.css","previous":20659,"size":0,"diff":-20659},{"filename":"route-Home.chunk.2dfcd.esm.js","previous":107689,"size":0,"diff":-107689},{"filename":"bundle.46323.js","previous":7236,"size":0,"diff":-7236},{"filename":"polyfills.1c45d.js","previous":2019,"size":0,"diff":-2019},{"filename":"route-Home.chunk.b0507.js","previous":108469,"size":0,"diff":-108469},{"filename":"ssr-bundle.d8f82.css","previous":0,"size":6822,"diff":6822},{"filename":"ssr-bundle.js","previous":0,"size":117713,"diff":117713}]},{"timestamp":1587975966494,"files":[{"filename":"ssr-bundle.d8f82.css","previous":6822,"size":0,"diff":-6822},{"filename":"ssr-bundle.js","previous":117717,"size":0,"diff":-117717},{"filename":"sw-esm.js","previous":0,"size":747,"diff":747},{"filename":"sw.js","previous":0,"size":744,"diff":744},{"filename":"bundle.042ca.esm.js","previous":0,"size":7275,"diff":7275},{"filename":"polyfills.7a9c4.esm.js","previous":0,"size":2019,"diff":2019},{"filename":"route-Home.chunk.d8f82.css","previous":0,"size":20659,"diff":20659},{"filename":"route-Home.chunk.2dfcd.esm.js","previous":0,"size":107689,"diff":107689},{"filename":"bundle.46323.js","previous":0,"size":7236,"diff":7236},{"filename":"polyfills.1c45d.js","previous":0,"size":2019,"diff":2019},{"filename":"route-Home.chunk.b0507.js","previous":0,"size":108469,"diff":108469}]},{"timestamp":1587975899255,"files":[{"filename":"sw-esm.js","previous":747,"size":0,"diff":-747},{"filename":"sw.js","previous":744,"size":0,"diff":-744},{"filename":"bundle.042ca.esm.js","previous":7275,"size":0,"diff":-7275},{"filename":"polyfills.7a9c4.esm.js","previous":2019,"size":0,"diff":-2019},{"filename":"route-Home.chunk.d8f82.css","previous":20659,"size":0,"diff":-20659},{"filename":"route-Home.chunk.2dfcd.esm.js","previous":107689,"size":0,"diff":-107689},{"filename":"bundle.46323.js","previous":7236,"size":0,"diff":-7236},{"filename":"polyfills.1c45d.js","previous":2019,"size":0,"diff":-2019},{"filename":"route-Home.chunk.b0507.js","previous":108469,"size":0,"diff":-108469},{"filename":"ssr-bundle.d8f82.css","previous":0,"size":6822,"diff":6822},{"filename":"ssr-bundle.js","previous":0,"size":117717,"diff":117717}]},{"timestamp":1587975799801,"files":[{"filename":"ssr-bundle.d8f82.css","previous":6822,"size":0,"diff":-6822},{"filename":"ssr-bundle.js","previous":117717,"size":0,"diff":-117717},{"filename":"sw-esm.js","previous":0,"size":747,"diff":747},{"filename":"sw.js","previous":0,"size":744,"diff":744},{"filename":"bundle.042ca.esm.js","previous":0,"size":7275,"diff":7275},{"filename":"polyfills.7a9c4.esm.js","previous":0,"size":2019,"diff":2019},{"filename":"route-Home.chunk.d8f82.css","previous":0,"size":20659,"diff":20659},{"filename":"route-Home.chunk.2dfcd.esm.js","previous":0,"size":107689,"diff":107689},{"filename":"bundle.46323.js","previous":0,"size":7236,"diff":7236},{"filename":"polyfills.1c45d.js","previous":0,"size":2019,"diff":2019},{"filename":"route-Home.chunk.b0507.js","previous":0,"size":108469,"diff":108469}]},{"timestamp":1587975730216,"files":[{"filename":"sw-esm.js","previous":747,"size":0,"diff":-747},{"filename":"sw.js","previous":744,"size":0,"diff":-744},{"filename":"route-Home.chunk.d8f82.css","previous":20659,"size":0,"diff":-20659},{"filename":"route-Home.chunk.2dfcd.esm.js","previous":107689,"size":0,"diff":-107689},{"filename":"route-Home.chunk.b0507.js","previous":108469,"size":0,"diff":-108469},{"filename":"bundle.e3b6f.esm.js","previous":7202,"size":0,"diff":-7202},{"filename":"polyfills.7a9c4.esm.js","previous":2019,"size":0,"diff":-2019},{"filename":"bundle.e2e8d.js","previous":7190,"size":0,"diff":-7190},{"filename":"polyfills.1c45d.js","previous":2019,"size":0,"diff":-2019},{"filename":"ssr-bundle.d8f82.css","previous":0,"size":6822,"diff":6822},{"filename":"ssr-bundle.js","previous":0,"size":117717,"diff":117717}]},{"timestamp":1587970462930,"files":[{"filename":"sw-esm.js","previous":741,"size":747,"diff":6},{"filename":"sw.js","previous":738,"size":744,"diff":6},{"filename":"polyfills.851f4.esm.js","previous":2012,"size":0,"diff":-2012},{"filename":"route-Home.chunk.d8f82.css","previous":20659,"size":20659,"diff":0},{"filename":"route-Home.chunk.2dfcd.esm.js","previous":107689,"size":107689,"diff":0},{"filename":"polyfills.1a596.js","previous":2013,"size":0,"diff":-2013},{"filename":"route-Home.chunk.b0507.js","previous":108469,"size":108469,"diff":0},{"filename":"bundle.fc8d8.esm.js","previous":7194,"size":0,"diff":-7194},{"filename":"bundle.ea6bb.js","previous":7184,"size":0,"diff":-7184},{"filename":"bundle.e3b6f.esm.js","previous":0,"size":7202,"diff":7202},{"filename":"polyfills.7a9c4.esm.js","previous":0,"size":2019,"diff":2019},{"filename":"bundle.e2e8d.js","previous":0,"size":7190,"diff":7190},{"filename":"polyfills.1c45d.js","previous":0,"size":2019,"diff":2019}]},{"timestamp":1587959717071,"files":[{"filename":"sw-esm.js","previous":741,"size":741,"diff":0},{"filename":"sw.js","previous":738,"size":738,"diff":0},{"filename":"bundle.c5971.esm.js","previous":7252,"size":0,"diff":-7252},{"filename":"polyfills.851f4.esm.js","previous":2012,"size":2012,"diff":0},{"filename":"route-Home.chunk.d8f82.css","previous":20659,"size":20659,"diff":0},{"filename":"route-Home.chunk.2dfcd.esm.js","previous":107689,"size":107689,"diff":0},{"filename":"bundle.a352b.js","previous":7223,"size":0,"diff":-7223},{"filename":"polyfills.1a596.js","previous":2013,"size":2013,"diff":0},{"filename":"route-Home.chunk.b0507.js","previous":108469,"size":108469,"diff":0},{"filename":"bundle.fc8d8.esm.js","previous":0,"size":7194,"diff":7194},{"filename":"bundle.ea6bb.js","previous":0,"size":7184,"diff":7184}]},{"timestamp":1587959625215,"files":[{"filename":"ssr-bundle.d8f82.css","previous":6822,"size":0,"diff":-6822},{"filename":"ssr-bundle.js","previous":117705,"size":0,"diff":-117705},{"filename":"sw-esm.js","previous":0,"size":741,"diff":741},{"filename":"sw.js","previous":0,"size":738,"diff":738},{"filename":"bundle.c5971.esm.js","previous":0,"size":7252,"diff":7252},{"filename":"polyfills.851f4.esm.js","previous":0,"size":2012,"diff":2012},{"filename":"route-Home.chunk.d8f82.css","previous":0,"size":20659,"diff":20659},{"filename":"route-Home.chunk.2dfcd.esm.js","previous":0,"size":107689,"diff":107689},{"filename":"bundle.a352b.js","previous":0,"size":7223,"diff":7223},{"filename":"polyfills.1a596.js","previous":0,"size":2013,"diff":2013},{"filename":"route-Home.chunk.b0507.js","previous":0,"size":108469,"diff":108469}]},{"timestamp":1587959562476,"files":[{"filename":"sw-esm.js","previous":741,"size":0,"diff":-741},{"filename":"sw.js","previous":738,"size":0,"diff":-738},{"filename":"bundle.c5971.esm.js","previous":7252,"size":0,"diff":-7252},{"filename":"polyfills.851f4.esm.js","previous":2012,"size":0,"diff":-2012},{"filename":"route-Home.chunk.d8f82.css","previous":20659,"size":0,"diff":-20659},{"filename":"route-Home.chunk.2dfcd.esm.js","previous":107689,"size":0,"diff":-107689},{"filename":"bundle.a352b.js","previous":7223,"size":0,"diff":-7223},{"filename":"polyfills.1a596.js","previous":2013,"size":0,"diff":-2013},{"filename":"route-Home.chunk.b0507.js","previous":108469,"size":0,"diff":-108469},{"filename":"ssr-bundle.d8f82.css","previous":0,"size":6822,"diff":6822},{"filename":"ssr-bundle.js","previous":0,"size":117705,"diff":117705}]},{"timestamp":1587914605598,"files":[{"filename":"ssr-bundle.d8f82.css","previous":6822,"size":0,"diff":-6822},{"filename":"ssr-bundle.js","previous":117705,"size":0,"diff":-117705},{"filename":"sw-esm.js","previous":0,"size":741,"diff":741},{"filename":"sw.js","previous":0,"size":738,"diff":738},{"filename":"bundle.c5971.esm.js","previous":0,"size":7252,"diff":7252},{"filename":"polyfills.851f4.esm.js","previous":0,"size":2012,"diff":2012},{"filename":"route-Home.chunk.d8f82.css","previous":0,"size":20659,"diff":20659},{"filename":"route-Home.chunk.2dfcd.esm.js","previous":0,"size":107689,"diff":107689},{"filename":"bundle.a352b.js","previous":0,"size":7223,"diff":7223},{"filename":"polyfills.1a596.js","previous":0,"size":2013,"diff":2013},{"filename":"route-Home.chunk.b0507.js","previous":0,"size":108469,"diff":108469}]},{"timestamp":1587914508131,"files":[{"filename":"ssr-bundle.d8f82.css","previous":0,"size":6822,"diff":6822},{"filename":"ssr-bundle.js","previous":0,"size":117705,"diff":117705}]}]
