[{"timestamp":1587959717071,"files":[{"filename":"sw-esm.js","previous":741,"size":741,"diff":0},{"filename":"sw.js","previous":738,"size":738,"diff":0},{"filename":"bundle.c5971.esm.js","previous":7252,"size":0,"diff":-7252},{"filename":"polyfills.851f4.esm.js","previous":2012,"size":2012,"diff":0},{"filename":"route-Home.chunk.d8f82.css","previous":20659,"size":20659,"diff":0},{"filename":"route-Home.chunk.2dfcd.esm.js","previous":107689,"size":107689,"diff":0},{"filename":"bundle.a352b.js","previous":7223,"size":0,"diff":-7223},{"filename":"polyfills.1a596.js","previous":2013,"size":2013,"diff":0},{"filename":"route-Home.chunk.b0507.js","previous":108469,"size":108469,"diff":0},{"filename":"bundle.fc8d8.esm.js","previous":0,"size":7194,"diff":7194},{"filename":"bundle.ea6bb.js","previous":0,"size":7184,"diff":7184}]},{"timestamp":1587959625215,"files":[{"filename":"ssr-bundle.d8f82.css","previous":6822,"size":0,"diff":-6822},{"filename":"ssr-bundle.js","previous":117705,"size":0,"diff":-117705},{"filename":"sw-esm.js","previous":0,"size":741,"diff":741},{"filename":"sw.js","previous":0,"size":738,"diff":738},{"filename":"bundle.c5971.esm.js","previous":0,"size":7252,"diff":7252},{"filename":"polyfills.851f4.esm.js","previous":0,"size":2012,"diff":2012},{"filename":"route-Home.chunk.d8f82.css","previous":0,"size":20659,"diff":20659},{"filename":"route-Home.chunk.2dfcd.esm.js","previous":0,"size":107689,"diff":107689},{"filename":"bundle.a352b.js","previous":0,"size":7223,"diff":7223},{"filename":"polyfills.1a596.js","previous":0,"size":2013,"diff":2013},{"filename":"route-Home.chunk.b0507.js","previous":0,"size":108469,"diff":108469}]},{"timestamp":1587959562476,"files":[{"filename":"sw-esm.js","previous":741,"size":0,"diff":-741},{"filename":"sw.js","previous":738,"size":0,"diff":-738},{"filename":"bundle.c5971.esm.js","previous":7252,"size":0,"diff":-7252},{"filename":"polyfills.851f4.esm.js","previous":2012,"size":0,"diff":-2012},{"filename":"route-Home.chunk.d8f82.css","previous":20659,"size":0,"diff":-20659},{"filename":"route-Home.chunk.2dfcd.esm.js","previous":107689,"size":0,"diff":-107689},{"filename":"bundle.a352b.js","previous":7223,"size":0,"diff":-7223},{"filename":"polyfills.1a596.js","previous":2013,"size":0,"diff":-2013},{"filename":"route-Home.chunk.b0507.js","previous":108469,"size":0,"diff":-108469},{"filename":"ssr-bundle.d8f82.css","previous":0,"size":6822,"diff":6822},{"filename":"ssr-bundle.js","previous":0,"size":117705,"diff":117705}]},{"timestamp":1587914605598,"files":[{"filename":"ssr-bundle.d8f82.css","previous":6822,"size":0,"diff":-6822},{"filename":"ssr-bundle.js","previous":117705,"size":0,"diff":-117705},{"filename":"sw-esm.js","previous":0,"size":741,"diff":741},{"filename":"sw.js","previous":0,"size":738,"diff":738},{"filename":"bundle.c5971.esm.js","previous":0,"size":7252,"diff":7252},{"filename":"polyfills.851f4.esm.js","previous":0,"size":2012,"diff":2012},{"filename":"route-Home.chunk.d8f82.css","previous":0,"size":20659,"diff":20659},{"filename":"route-Home.chunk.2dfcd.esm.js","previous":0,"size":107689,"diff":107689},{"filename":"bundle.a352b.js","previous":0,"size":7223,"diff":7223},{"filename":"polyfills.1a596.js","previous":0,"size":2013,"diff":2013},{"filename":"route-Home.chunk.b0507.js","previous":0,"size":108469,"diff":108469}]},{"timestamp":1587914508131,"files":[{"filename":"ssr-bundle.d8f82.css","previous":0,"size":6822,"diff":6822},{"filename":"ssr-bundle.js","previous":0,"size":117705,"diff":117705}]}]
